{
  "layerConfig": {
    "deposits": {
      "label": "DEPOSITS",
      "displayFields": [
        {
          "key": "country",
          "label": "Country"
        },
        {
          "key": "depositType",
          "label": "Type"
        },
        {
          "key": "reserves",
          "label": "Reserves"
        },
        {
          "key": "status",
          "label": "Status"
        }
      ]
    },
    "miners": {
      "displayFields": [
        {
          "key": "country",
          "label": "Country"
        },
        {
          "key": "outputVolume",
          "label": "Extracted/yr"
        }
      ],
      "label": "MINERS"
    },
    "refiners": {
      "displayFields": [
        {
          "key": "country",
          "label": "Country"
        },
        {
          "key": "outputVolume",
          "label": "Output"
        },
        {
          "key": "products",
          "label": "Products"
        }
      ],
      "label": "REFINERS & RECYCLERS"
    },
    "supply": {
      "displayFields": [
        {
          "key": "totalVolume",
          "label": "Volume"
        },
        {
          "key": "marketSize",
          "label": "Market"
        }
      ],
      "label": "GLOBAL SUPPLY"
    },
    "gecl4": {
      "label": "GeCl₄ SUPPLIERS",
      "displayFields": [
        {
          "key": "country",
          "label": "Country"
        },
        {
          "key": "gecl4Output",
          "label": "GeCl₄ output"
        },
        {
          "key": "purity",
          "label": "Purity grade"
        }
      ]
    },
    "fibermfg": {
      "label": "FIBER MANUFACTURERS",
      "displayFields": [
        {
          "key": "country",
          "label": "Country"
        },
        {
          "key": "fiberOutput",
          "label": "Fiber capacity"
        },
        {
          "key": "geConsumption",
          "label": "Ge consumed/yr"
        }
      ]
    },
    "output": {
      "label": "OUTPUT",
      "displayFields": [
        {"key": "totalDeployed", "label": "Deployed/yr"},
        {"key": "aiGap", "label": "AI demand gap"}
      ]
    },
    "assembly": {
      "label": "ASSEMBLY",
      "displayFields": [
        {"key": "country", "label": "Country"},
        {"key": "annualRevenue", "label": "Revenue"},
        {"key": "primaryMarket", "label": "Primary market"}
      ]
    },
    "cableType": {
      "label": "CABLE TYPE",
      "displayFields": [
        {"key": "country", "label": ""},
        {"key": "fiberCount", "label": "Fiber count"},
        {"key": "keyOperators", "label": "Key operators"}
      ]
    },
    "integration": {
      "displayFields": [
        {
          "key": "country",
          "label": "Country"
        },
        {
          "key": "specialty",
          "label": "Specialty"
        }
      ],
      "label": "INTEGRATION"
    },
    "hyperscale": {
      "displayFields": [
        {
          "key": "ticker",
          "label": "Ticker"
        },
        {
          "key": "capex2025",
          "label": "2025 capex"
        }
      ],
      "label": "HYPERSCALE"
    },
    "recyclers": {
      "label": "RECYCLERS",
      "displayFields": [
        {
          "key": "country",
          "label": "Country"
        },
        {
          "key": "outputVolume",
          "label": "Output"
        },
        {
          "key": "specialty",
          "label": "Specialty"
        }
      ]
    },
    "supplyNodes": {
      "label": "SUPPLY",
      "displayFields": [
        {
          "key": "totalVolume",
          "label": "Volume"
        },
        {
          "key": "marketSize",
          "label": "Market"
        }
      ]
    }
  },
  "SPINE_TREE": {
    "Germanium": {
      "GeO₂ / GeCl₄": {
        "Fiber Optics": [
          "AI Datacenter"
        ]
      },
      "Ge Wafers": {
        "Space Solar": [
          "Satellites"
        ]
      }
    },
    "Copper": {
      "Cu Wire": {
        "Power Infrastructure": [
          "Data Centers",
          "EV Charging"
        ]
      }
    },
    "Silicon": {
      "Si Wafers": {
        "Semiconductors": [
          "AI Chips",
          "Logic ICs"
        ]
      }
    }
  },
  "EU_DATA": {
    "AI Datacenter": {
      "integration": [
        "Vertiv",
        "Equinix",
        "CoreWeave",
        "Schneider Electric",
        "CommScope",
        "AECOM"
      ],
      "hyperscale": [
        "Microsoft",
        "Google",
        "Amazon",
        "Meta",
        "xAI",
        "Oracle"
      ],
      "output": "AI Datacenter",
      "intToHyper": [
        [
          0,
          0
        ],
        [
          0,
          1
        ],
        [
          0,
          2
        ],
        [
          0,
          3
        ],
        [
          0,
          4
        ],
        [
          0,
          5
        ],
        [
          1,
          0
        ],
        [
          1,
          1
        ],
        [
          1,
          2
        ],
        [
          1,
          3
        ],
        [
          2,
          0
        ],
        [
          2,
          1
        ],
        [
          2,
          4
        ],
        [
          2,
          5
        ],
        [
          3,
          0
        ],
        [
          3,
          1
        ],
        [
          3,
          2
        ],
        [
          3,
          3
        ],
        [
          3,
          4
        ],
        [
          3,
          5
        ],
        [
          4,
          2
        ],
        [
          4,
          3
        ],
        [
          4,
          5
        ],
        [
          5,
          2
        ],
        [
          5,
          3
        ],
        [
          5,
          4
        ],
        [
          5,
          5
        ]
      ]
    }
  },
  "RAW_DATA": {
    "Germanium": {
      "deposits": [
        "Lincang",
        "Wulantuga",
        "Yimin",
        "Huize",
        "Yiliang + SYGT",
        "Spetsugli",
        "Big Hill",
        "Red Dog"
      ],
      "miners": [
        "Lincang Xinyuan",
        "Shengli Coal Group",
        "Various State Ops",
        "Yunnan Chihong",
        "JSC Germanium",
        "STL / Gécamines",
        "Teck Resources"
      ],
      "refiners": [
        "Lincang Xinyuan Refinery",
        "Smaller Chinese Refiners",
        "Yunnan Chihong Refinery",
        "JSC Germanium Refinery",
        "Umicore",
        "5N Plus",
        "PPM Pure Metals"
      ],
      "supplyNodes": [
        "China Primary Supply",
        "Western Recycled Supply"
      ],
      "supply": "Global Supply",
      "depToMin": [
        [
          0,
          0
        ],
        [
          1,
          1
        ],
        [
          2,
          2
        ],
        [
          3,
          3
        ],
        [
          4,
          3
        ],
        [
          5,
          4
        ],
        [
          6,
          5
        ],
        [
          7,
          6
        ]
      ],
      "minToRef": [
        [
          0,
          0
        ],
        [
          1,
          1
        ],
        [
          2,
          1
        ],
        [
          3,
          2
        ],
        [
          4,
          3
        ],
        [
          5,
          4
        ],
        [
          6,
          5
        ]
      ],
      "refToSupply": [
        [
          0,
          0
        ],
        [
          1,
          0
        ],
        [
          2,
          0
        ],
        [
          3,
          1
        ],
        [
          4,
          1
        ],
        [
          5,
          1
        ],
        [
          6,
          1
        ]
      ],
      "supplyToGlobal": [
        [
          0,
          0
        ],
        [
          1,
          0
        ]
      ],
      "minor": {
        "deposits": [
          2
        ],
        "miners": [
          2
        ],
        "refiners": []
      },
      "groupSplit": {
        "deposits": 5,
        "miners": 4
      }
    },
    "Copper": {
      "deposits": [
        "Escondida",
        "Collahuasi",
        "Antamina",
        "Cerro Verde",
        "El Teniente"
      ],
      "miners": [
        "BHP",
        "Glencore",
        "Antamina JV",
        "Freeport"
      ],
      "refiners": [
        "Codelco",
        "Atlantic Copper",
        "Aurubis"
      ],
      "supply": "Global Supply",
      "depToMin": [
        [
          0,
          0
        ],
        [
          1,
          1
        ],
        [
          2,
          2
        ],
        [
          3,
          3
        ],
        [
          4,
          0
        ]
      ],
      "minToRef": [
        [
          0,
          0
        ],
        [
          1,
          1
        ],
        [
          2,
          2
        ],
        [
          3,
          0
        ]
      ],
      "minor": {
        "deposits": [],
        "miners": [],
        "refiners": []
      }
    },
    "Silicon": {
      "deposits": [
        "Spruce Pine",
        "Orissa Belt",
        "Minas Gerais",
        "Quartz Hill"
      ],
      "miners": [
        "The Quartz Corp",
        "CUMI",
        "Rima Industrial"
      ],
      "refiners": [
        "Wacker Chemie",
        "Shin-Etsu",
        "Hemlock Semi"
      ],
      "supply": "Global Supply",
      "depToMin": [
        [
          0,
          0
        ],
        [
          1,
          1
        ],
        [
          2,
          2
        ],
        [
          3,
          0
        ]
      ],
      "minToRef": [
        [
          0,
          0
        ],
        [
          1,
          1
        ],
        [
          2,
          2
        ]
      ],
      "minor": {
        "deposits": [],
        "miners": [],
        "refiners": []
      }
    }
  },
  "COMP_DATA": {
    "GeO₂ / GeCl₄": {
      "geCl4": [
        "Umicore GeCl4",
        "Yunnan Chihong GeCl4",
        "Chinese State GeCl4 Plants",
        "JSC Germanium GeCl4"
      ],
      "fiberMfg": [
        "Corning",
        "Prysmian",
        "Fujikura",
        "Sumitomo Electric",
        "Shin-Etsu",
        "YOFC"
      ],
      "output": "Optical Fiber Strand",
      "geCl4ToFiber": [
        [0,0],[0,1],[0,2],[1,3],[1,4],[1,5],[2,3],[2,4],[2,5],[3,3]
      ],
      "fiberToOutput": [
        [0,0],[1,0],[2,0],[3,0],[4,0],[5,0]
      ],
      "minor": {
        "geCl4": [3],
        "fiberMfg": []
      }
    }
  },
  "SUB_DATA": {
    "Fiber Optics": {
      "assembly": [
        "Corning",
        "Prysmian",
        "Fujikura",
        "Sumitomo Electric",
        "CommScope",
        "AFL",
        "Alcatel SN",
        "SubCom",
        "NEC"
      ],
      "cableType": [
        "Datacenter Cable",
        "Terrestrial Long-Haul",
        "Subsea Cable"
      ],
      "output": "Fiber Optic Cable",
      "assToType": [
        [
          0,
          0
        ],
        [
          0,
          1
        ],
        [
          1,
          0
        ],
        [
          1,
          1
        ],
        [
          2,
          0
        ],
        [
          2,
          1
        ],
        [
          3,
          0
        ],
        [
          3,
          1
        ],
        [
          4,
          0
        ],
        [
          4,
          1
        ],
        [
          5,
          0
        ],
        [
          5,
          1
        ],
        [
          6,
          2
        ],
        [
          7,
          2
        ],
        [
          8,
          2
        ]
      ],
      "minor": {
        "assembly": [],
        "cableType": []
      }
    }
  }
}